LICENSE
MANIFEST.in
README.rst
setup.py
charisma_django/__init__.py
charisma_django/admin.py
charisma_django/apps.py
charisma_django/models.py
charisma_django/tests.py
charisma_django/urls.py
charisma_django/views.py
charisma_django/migrations/0001_initial.py
charisma_django/migrations/__init__.py
charisma_django/static/charisma_django/bower_components/bootstrap/.bower.json
charisma_django/static/charisma_django/bower_components/bootstrap/Gruntfile.js
charisma_django/static/charisma_django/bower_components/bootstrap/LICENSE
charisma_django/static/charisma_django/bower_components/bootstrap/README.md
charisma_django/static/charisma_django/bower_components/bootstrap/bower.json
charisma_django/static/charisma_django/bower_components/bootstrap/package.json
charisma_django/static/charisma_django/bower_components/bootstrap-tour/.bower.json
charisma_django/static/charisma_django/bower_components/bootstrap-tour/.gitignore
charisma_django/static/charisma_django/bower_components/bootstrap-tour/.travis.yml
charisma_django/static/charisma_django/bower_components/bootstrap-tour/Gruntfile.coffee
charisma_django/static/charisma_django/bower_components/bootstrap-tour/LICENSE
charisma_django/static/charisma_django/bower_components/bootstrap-tour/README.md
charisma_django/static/charisma_django/bower_components/bootstrap-tour/bower.json
charisma_django/static/charisma_django/bower_components/bootstrap-tour/composer.json
charisma_django/static/charisma_django/bower_components/bootstrap-tour/index.html
charisma_django/static/charisma_django/bower_components/bootstrap-tour/package.json
charisma_django/static/charisma_django/bower_components/bootstrap-tour/build/css/bootstrap-tour.css
charisma_django/static/charisma_django/bower_components/bootstrap-tour/build/css/bootstrap-tour.min.css
charisma_django/static/charisma_django/bower_components/bootstrap-tour/build/js/bootstrap-tour.js
charisma_django/static/charisma_django/bower_components/bootstrap-tour/build/js/bootstrap-tour.min.js
django_charisma.egg-info/PKG-INFO
django_charisma.egg-info/SOURCES.txt
django_charisma.egg-info/dependency_links.txt
django_charisma.egg-info/top_level.txt